{
    "title":"Public Toilet - Princes Park Royal Parade (near Park Street)",
    "lat":-37.77893699,
    "lng":144.9604666
  },
  {
    "title":"Public Toilet - Princes Park South Playground (Princes Park Drive)",
    "lat":-37.78559839,
    "lng":144.9630354
  },
  {
    "title":"Public Toilet - Royal Park, Wetland (off Oak Street)",
    "lat":-37.78303248,
    "lng":144.9418564
  },
  {
    "title":"Public Toilet - Docklands Park South - 25 Harbour Esplanade",
    "lat":-37.8217586,
    "lng":144.9473834
  },
  {
    "title":"Public Toilet - Alexandra Gardens (Riverslide Skate Park)",
    "lat":-37.82035527,
    "lng":144.9733129
  },
  {
    "title":"Public Toilet - Birrarung Marr Speakers Corner",
    "lat":-37.82100478,
    "lng":144.9759332
  },
  {
    "title":"Public Toilet - Queen Victoria Market (465 Queen Street)",
    "lat":-37.807864,
    "lng":144.9579478
  },
  {
    "title":"Public Toilet - Argyle Place North (Opposite 4 Argyle Place North)",
    "lat":-37.80207629,
    "lng":144.966424
  },
  {
    "title":"Public Toilet - Batman Park (2A Spencer Street)",
    "lat":-37.82172068,
    "lng":144.9555781
  },
  {
    "title":"Public Toilet - Lincoln Square (138-142 Bouverie Street)",
    "lat":-37.80271182,
    "lng":144.9622681
  },
  {
    "title":"Public Toilet - Point Park (Point Park Crescent)",
    "lat":-37.82331083,
    "lng":144.9418276
  },
  {
    "title":"Public Toilet - Flinders Street (No 245 Flinders Street Station)",
    "lat":-37.8179032,
    "lng":144.9662643
  },
  {
    "title":"Public Toilet - Queen Street (opposite 113 Queen Street)",
    "lat":-37.81583817,
    "lng":144.9610621
  },
  {
    "title":"Public Toilet - Royal Park (Flemington Rd - Near North Park Tennis Club)",
    "lat":-37.79017441,
    "lng":144.9436691
  },
  {
    "title":"Public Toilet - JJ Holland Park (Opposite, 48 Altona Street)",
    "lat":-37.79812546,
    "lng":144.9264247
  },
  {
    "title":"Public Toilet - Birrarung Marr (Opposite Artplay)",
    "lat":-37.81859887,
    "lng":144.9710596
  },
  {
    "title":"Public Toilet - Bourke Street (opposite 225 Bourke Street)",
    "lat":-37.81324543,
    "lng":144.9668966
  },
  {
    "title":"Public Toilet - Carlton Gardens North (Opposite 199 Rathdowne Street)",
    "lat":-37.80264556,
    "lng":144.9698213
  },
  {
    "title":"Public Toilet - Exhibition Street (Opposite 77 Exhibition Street)",
    "lat":-37.81384642,
    "lng":144.9713741
  },
  {
    "title":"Public Toilet - Lonsdale Street (Opposite 581 Lonsdale Street)",
    "lat":-37.81434552,
    "lng":144.9551179
  },
  {
    "title":"Public Toilet - Market Street (Opposite 74 Market Street)",
    "lat":-37.81746989,
    "lng":144.9602543
  },
  {
    "title":"Public Toilet - Bellair Street (Opposite 180 Bellair Street)",
    "lat":-37.79373229,
    "lng":144.9303519
  },
  {
    "title":"Public Toilet - Kings Domain South (Opposite 169 Domain Road)",
    "lat":-37.83393827,
    "lng":144.981784
  },
  {
    "title":"Public Toilet - Flinders Street (No. 399 Flinders St.)",
    "lat":-37.81940611,
    "lng":144.9612768
  },
  {
    "title":"Public Toilet - Kings Domain South (off Birdwood Avenue)",
    "lat":-37.83085749,
    "lng":144.9751694
  },
  {
    "title":"Public Toilet - Lonsdale Street (Opposite 424 Lonsdale Street)",
    "lat":-37.8129331,
    "lng":144.9600121
  },
  {
    "title":"Public Toilet - Lonsdale Street (Opposite 88 Lonsdale Street)",
    "lat":-37.81003568,
    "lng":144.9699025
  },
  {
    "title":"Public Toilet - Franklin Street (Opposite 80 Franklin Street)",
    "lat":-37.80823545,
    "lng":144.9601898
  },
  {
    "title":"Public Toilet - Kings Domain Myer Music Bowl Rear of",
    "lat":-37.8228916,
    "lng":144.975281
  },
  {
    "title":"Public Toilet - Carlton Gardens South (Opposite 39 Rathdowne Street)",
    "lat":-37.80625893,
    "lng":144.9692027
  },
  {
    "title":"Public Toilet - Fitzroy Gardens Toilets (150 Clarendon Street)",
    "lat":-37.81203206,
    "lng":144.9830797
  },
  {
    "title":"Public Toilet - Town Hall Melbourne (200 Collins Street)",
    "lat":-37.81521577,
    "lng":144.9669433
  },
  {
    "title":"Public Toilet - Victoria Harbour, Shed 2 (North Wharf Road)",
    "lat":-37.81893395,
    "lng":144.9342022
  },
  {
    "title":"Public Toilet - Saint Mangos Lane, The Palladio (New Quay)",
    "lat":-37.81435831,
    "lng":144.9416822
  },
  {
    "title":"Public Toilet - Fawkner Park, Opposite 55 Commercial Road",
    "lat":-37.84520656,
    "lng":144.9826144
  },
  {
    "title":"Public Toilet - Fawkner Park, Opposite 150W Toorak Road",
    "lat":-37.83825284,
    "lng":144.9843892
  },
  {
    "title":"Public Toilet - Fitzroy Gardens (2 Lansdowne Street)",
    "lat":-37.81528281,
    "lng":144.9775933
  },
  {
    "title":"Public Toilet - Ievers Reserve - Flemington Road",
    "lat":-37.796799,
    "lng":144.9519667
  },
  {
    "title":"Public Toilet - Southbank Promenade (opposite Esso House)",
    "lat":-37.82034213,
    "lng":144.9642197
  },
  {
    "title":"Public Toilet - Alexandra Park",
    "lat":-37.82764305,
    "lng":144.9818117
  },
  {
    "title":"Public Toilet - Flagstaff Gardens (cnr William & Dudley)",
    "lat":-37.80892048,
    "lng":144.9550433
  },
  {
    "title":"Public Toilet - JJ Holland Park, Skate Park (113 Kensington Road)",
    "lat":-37.79806402,
    "lng":144.9211058
  },
  {
    "title":"Public Toilet - Powlett Reserve (Opposite 128 Albert Street)",
    "lat":-37.81094233,
    "lng":144.9868587
  },
  {
    "title":"Public Toilet - Royal Park - Native Garden (off Gatehouse Street)",
    "lat":-37.79251146,
    "lng":144.9568517
  },
  {
    "title":"Public Toilet - Treasury Gardens (Store and Toilet)",
    "lat":-37.81341843,
    "lng":144.977467
  },
  {
    "title":"Public Toilet - Goschs Paddock (112 Olympic Boulevard)",
    "lat":-37.82438829,
    "lng":144.9856629
  },
  {
    "title":"Public Toilet - Queen Victoria Gardens (Linlithgow Avenue)",
    "lat":-37.82294829,
    "lng":144.9709857
  }